slurmpie/__init__.py
slurmpie/slurmpie.py
tests/__init__.py
tests/test_jobs.py
tests/test_pipeline.py
slurmpie-0.9.0.dist-info/LICENSE
slurmpie-0.9.0.dist-info/METADATA
slurmpie-0.9.0.dist-info/WHEEL
slurmpie-0.9.0.dist-info/top_level.txt
slurmpie-0.9.0.dist-info/RECORD
