Metadata-Version: 2.1
Name: slurmpie
Version: 0.9.0
Summary: Package to interact with SLURM
Home-page: https://github.com/svdvoort/slurmpie
Author: Sebastian van der Voort
Author-email: Svdvoort@users.noreply.github.com
License: UNKNOWN
Platform: UNKNOWN
Classifier: Programming Language :: Python :: 3
Classifier: License :: OSI Approved :: MIT License
Classifier: Operating System :: OS Independent
Requires-Python: >=3.6
